splendaq/__init__.py
splendaq/_cli.py
splendaq/_version.py
splendaq/control/__init__.py
splendaq/control/_hps.py
splendaq/control/_sr560.py
splendaq/daq/__init__.py
splendaq/daq/_log_data.py
splendaq/daq/_offline_trigger.py
splendaq/daq/_oscilloscope.py
splendaq/daq/_sequencer.py
splendaq/io/__init__.py
splendaq/io/_io.py
splendaq/io/_liconvert/COPYING.txt
splendaq/io/_liconvert/liconvert_linux
splendaq/io/_liconvert/liconvert_macos
splendaq/io/_liconvert/liconvert_windows.exe
splendaq-0.9.0.dist-info/licenses/LICENSE
splendaq-0.9.0.dist-info/METADATA
splendaq-0.9.0.dist-info/WHEEL
splendaq-0.9.0.dist-info/entry_points.txt
splendaq-0.9.0.dist-info/top_level.txt
splendaq-0.9.0.dist-info/RECORD
