Metadata-Version: 2.4
Name: splendaq
Version: 0.9.0
Summary: Generalized offline data acquisition with a focus on the Moku
Home-page: https://github.com/splendor-collab/splendaq
Author: SPLENDOR Collaboration
Maintainer: SPLENDOR Collaboration
License: MIT
Requires-Python: >=3.6
License-File: LICENSE
Requires-Dist: numpy
Requires-Dist: scipy
Requires-Dist: matplotlib
Requires-Dist: moku>=3.2.0
Requires-Dist: h5py
Requires-Dist: pyyaml
Requires-Dist: pyserial
Requires-Dist: tqdm
Dynamic: license-file
